[{"name":"infor_screen","qualifiedName":"infor_screen","href":"infor_screen/infor_screen-library.html","kind":9,"overriddenDepth":0,"packageRank":0,"desc":""},{"name":"InformationScreen","qualifiedName":"infor_screen.InformationScreen","href":"infor_screen/InformationScreen-class.html","kind":3,"overriddenDepth":0,"packageRank":0,"desc":"","enclosedBy":{"name":"infor_screen","kind":9,"href":"infor_screen/infor_screen-library.html"}},{"name":"InformationScreen","qualifiedName":"infor_screen.InformationScreen.InformationScreen","href":"infor_screen/InformationScreen/InformationScreen.html","kind":2,"overriddenDepth":0,"packageRank":0,"desc":"","enclosedBy":{"name":"InformationScreen","kind":3,"href":"infor_screen/InformationScreen-class.html"}},{"name":"age","qualifiedName":"infor_screen.InformationScreen.age","href":"infor_screen/InformationScreen/age.html","kind":16,"overriddenDepth":0,"packageRank":0,"desc":"","enclosedBy":{"name":"InformationScreen","kind":3,"href":"infor_screen/InformationScreen-class.html"}},{"name":"build","qualifiedName":"infor_screen.InformationScreen.build","href":"infor_screen/InformationScreen/build.html","kind":10,"overriddenDepth":1,"packageRank":0,"desc":"Describes the part of the user interface represented by this widget.","enclosedBy":{"name":"InformationScreen","kind":3,"href":"infor_screen/InformationScreen-class.html"}},{"name":"diastolic","qualifiedName":"infor_screen.InformationScreen.diastolic","href":"infor_screen/InformationScreen/diastolic.html","kind":16,"overriddenDepth":0,"packageRank":0,"desc":"","enclosedBy":{"name":"InformationScreen","kind":3,"href":"infor_screen/InformationScreen-class.html"}},{"name":"getAgeRange","qualifiedName":"infor_screen.InformationScreen.getAgeRange","href":"infor_screen/InformationScreen/getAgeRange.html","kind":10,"overriddenDepth":0,"packageRank":0,"desc":"","enclosedBy":{"name":"InformationScreen","kind":3,"href":"infor_screen/InformationScreen-class.html"}},{"name":"getAgeRanges","qualifiedName":"infor_screen.InformationScreen.getAgeRanges","href":"infor_screen/InformationScreen/getAgeRanges.html","kind":10,"overriddenDepth":0,"packageRank":0,"desc":"","enclosedBy":{"name":"InformationScreen","kind":3,"href":"infor_screen/InformationScreen-class.html"}},{"name":"getCategory","qualifiedName":"infor_screen.InformationScreen.getCategory","href":"infor_screen/InformationScreen/getCategory.html","kind":10,"overriddenDepth":0,"packageRank":0,"desc":"","enclosedBy":{"name":"InformationScreen","kind":3,"href":"infor_screen/InformationScreen-class.html"}},{"name":"showInfoDialog","qualifiedName":"infor_screen.InformationScreen.showInfoDialog","href":"infor_screen/InformationScreen/showInfoDialog.html","kind":10,"overriddenDepth":0,"packageRank":0,"desc":"","enclosedBy":{"name":"InformationScreen","kind":3,"href":"infor_screen/InformationScreen-class.html"}},{"name":"systolic","qualifiedName":"infor_screen.InformationScreen.systolic","href":"infor_screen/InformationScreen/systolic.html","kind":16,"overriddenDepth":0,"packageRank":0,"desc":"","enclosedBy":{"name":"InformationScreen","kind":3,"href":"infor_screen/InformationScreen-class.html"}},{"name":"main","qualifiedName":"infor_screen.main","href":"infor_screen/main.html","kind":8,"overriddenDepth":0,"packageRank":0,"desc":"","enclosedBy":{"name":"infor_screen","kind":9,"href":"infor_screen/infor_screen-library.html"}},{"name":"input_screen","qualifiedName":"input_screen","href":"input_screen/input_screen-library.html","kind":9,"overriddenDepth":0,"packageRank":0,"desc":""},{"name":"InputScreen","qualifiedName":"input_screen.InputScreen","href":"input_screen/InputScreen-class.html","kind":3,"overriddenDepth":0,"packageRank":0,"desc":"","enclosedBy":{"name":"input_screen","kind":9,"href":"input_screen/input_screen-library.html"}},{"name":"InputScreen","qualifiedName":"input_screen.InputScreen.InputScreen","href":"input_screen/InputScreen/InputScreen.html","kind":2,"overriddenDepth":0,"packageRank":0,"desc":"","enclosedBy":{"name":"InputScreen","kind":3,"href":"input_screen/InputScreen-class.html"}},{"name":"build","qualifiedName":"input_screen.InputScreen.build","href":"input_screen/InputScreen/build.html","kind":10,"overriddenDepth":1,"packageRank":0,"desc":"Describes the part of the user interface represented by this widget.","enclosedBy":{"name":"InputScreen","kind":3,"href":"input_screen/InputScreen-class.html"}},{"name":"main","qualifiedName":"main","href":"main/main-library.html","kind":9,"overriddenDepth":0,"packageRank":0,"desc":""},{"name":"MyApp","qualifiedName":"main.MyApp","href":"main/MyApp-class.html","kind":3,"overriddenDepth":0,"packageRank":0,"desc":"","enclosedBy":{"name":"main","kind":9,"href":"main/main-library.html"}},{"name":"MyApp","qualifiedName":"main.MyApp.MyApp","href":"main/MyApp/MyApp.html","kind":2,"overriddenDepth":0,"packageRank":0,"desc":"","enclosedBy":{"name":"MyApp","kind":3,"href":"main/MyApp-class.html"}},{"name":"build","qualifiedName":"main.MyApp.build","href":"main/MyApp/build.html","kind":10,"overriddenDepth":1,"packageRank":0,"desc":"Describes the part of the user interface represented by this widget.","enclosedBy":{"name":"MyApp","kind":3,"href":"main/MyApp-class.html"}},{"name":"main","qualifiedName":"main.main","href":"main/main.html","kind":8,"overriddenDepth":0,"packageRank":0,"desc":"","enclosedBy":{"name":"main","kind":9,"href":"main/main-library.html"}}]
